ruins/__init__.py
ruins/apps/__init__.py
ruins/apps/bubbles.py
ruins/apps/extremes.py
ruins/apps/landuse.py
ruins/apps/sunburst.py
ruins/apps/temperature_shift.py
ruins/apps/uncertainty.py
ruins/apps/weather.py
ruins/components/__init__.py
ruins/components/data_select.py
ruins/components/model_scale_select.py
ruins/core/__init__.py
ruins/core/build.py
ruins/core/cache.py
ruins/core/config.py
ruins/core/data_manager.py
ruins/core/debug_view.py
ruins/core/i18n.py
ruins/plotting/__init__.py
ruins/plotting/bubble_plot.py
ruins/plotting/climate_data.py
ruins/plotting/climate_indices.py
ruins/plotting/climate_parcoords.py
ruins/plotting/cordex_sunburst.py
ruins/plotting/distribution_shift.py
ruins/plotting/dists.py
ruins/plotting/floodmodel.py
ruins/plotting/kde.py
ruins/plotting/maps.py
ruins/plotting/pdsi.py
ruins/plotting/stripes_heatmap.py
ruins/plotting/weather_data.py
ruins/plotting/windpower.py
ruins/processing/__init__.py
ruins/processing/climate_indices.py
ruins/processing/drain_cap.py
ruins/processing/pdsi.py
ruins/processing/sdm.py
ruins/processing/sunburst.py
ruins/processing/windpower.py
ruins_app-0.19.0.dist-info/LICENSE
ruins_app-0.19.0.dist-info/METADATA
ruins_app-0.19.0.dist-info/WHEEL
ruins_app-0.19.0.dist-info/top_level.txt
ruins_app-0.19.0.dist-info/RECORD
