Metadata-Version: 2.1
Name: ruins-app
Version: 0.19.0
Summary: Climate change and uncertainty explorer
Author: Conrad Jackisch, Mirko Mälicke
Author-email: Conrad.Jackisch@tbt.tu-freiberg.de, mirko@hydrocode.de
License-File: LICENSE
Requires-Dist: numpy
Requires-Dist: streamlit (>=1.9.0)
Requires-Dist: pandas
Requires-Dist: scipy
Requires-Dist: seaborn
Requires-Dist: plotly (>=4.5.0)
Requires-Dist: statsmodels
Requires-Dist: xarray
Requires-Dist: climate-indices
Requires-Dist: pillow
Requires-Dist: sklearn
Requires-Dist: fire
Requires-Dist: requests
Requires-Dist: protobuf (<4.0.0)
Requires-Dist: typing-extensions
Requires-Dist: streamlit-graphic-slider
Requires-Dist: scikit-image
